wsic/__init__.py
wsic/cli.py
wsic/codecs.py
wsic/dicom.py
wsic/enums.py
wsic/magic.py
wsic/multiproc.py
wsic/readers.py
wsic/tile_iterators.py
wsic/typedefs.py
wsic/utils.py
wsic/validation.py
wsic/writers.py
wsic/data/__init__.py
wsic/data/sRGB_v4_ICC_preference.icc
wsic/metadata/__init__.py
wsic/metadata/ngff.py
wsic-0.9.0.dist-info/AUTHORS.md
wsic-0.9.0.dist-info/LICENSE
wsic-0.9.0.dist-info/METADATA
wsic-0.9.0.dist-info/WHEEL
wsic-0.9.0.dist-info/entry_points.txt
wsic-0.9.0.dist-info/top_level.txt
wsic-0.9.0.dist-info/RECORD
