Metadata-Version: 2.1
Name: wsic
Version: 0.9.0
Summary: Whole Slide Image (WSI) conversion for brightfield histology images
Home-page: https://github.com/john-p/wsic
Author: John Pocock
Author-email: j.c.pocock@warwick.ac.uk
Keywords: wsic
Classifier: Development Status :: 2 - Pre-Alpha
Classifier: Intended Audience :: Developers
Classifier: Natural Language :: English
Classifier: Programming Language :: Python :: 3
Classifier: Programming Language :: Python :: 3.8
Classifier: Programming Language :: Python :: 3.9
Classifier: Programming Language :: Python :: 3.10
Requires-Python: >=3.8
License-File: LICENSE
License-File: AUTHORS.md
Requires-Dist: numpy
Requires-Dist: zarr
Provides-Extra: all
Requires-Dist: pytest (>=3) ; extra == 'all'
Requires-Dist: opencv-python ; extra == 'all'
Requires-Dist: scipy ; extra == 'all'
Requires-Dist: scikit-image ; extra == 'all'
Requires-Dist: imagecodecs ; extra == 'all'
Requires-Dist: qoi ; extra == 'all'
Requires-Dist: sphinx ; extra == 'all'
Requires-Dist: sphinx-autoapi ; extra == 'all'
Requires-Dist: tifffile ; extra == 'all'
Requires-Dist: dask ; extra == 'all'
Requires-Dist: glymur ; extra == 'all'
Requires-Dist: xarray ; extra == 'all'
Requires-Dist: Click (>=7.0) ; extra == 'all'
Requires-Dist: tqdm ; extra == 'all'
Provides-Extra: cli
Requires-Dist: Click (>=7.0) ; extra == 'cli'
Provides-Extra: codecs
Requires-Dist: imagecodecs ; extra == 'codecs'
Requires-Dist: qoi ; extra == 'codecs'
Provides-Extra: docs
Requires-Dist: sphinx ; extra == 'docs'
Requires-Dist: sphinx-autoapi ; extra == 'docs'
Provides-Extra: formats
Requires-Dist: tifffile ; extra == 'formats'
Requires-Dist: dask ; extra == 'formats'
Requires-Dist: glymur ; extra == 'formats'
Requires-Dist: xarray ; extra == 'formats'
Provides-Extra: jpeg2000
Requires-Dist: glymur ; extra == 'jpeg2000'
Provides-Extra: performance
Requires-Dist: opencv-python ; extra == 'performance'
Provides-Extra: test
Requires-Dist: pytest (>=3) ; extra == 'test'
Requires-Dist: opencv-python ; extra == 'test'
Requires-Dist: scipy ; extra == 'test'
Requires-Dist: scikit-image ; extra == 'test'
Requires-Dist: imagecodecs ; extra == 'test'
Requires-Dist: qoi ; extra == 'test'
Provides-Extra: ux
Requires-Dist: tqdm ; extra == 'ux'
